[
    {
        "imagePath": "assets/images/page1.png",
        "color": "#F6B87B",
        "title": "Откройте для себя удивительные рецепты",
        "description": "Исследуйте мир вкусных рецептов, которыми делятся такие же кулинарные энтузиасты, как и вы. Вдохновляйтесь блюдами со всего мира!"
    },
    {
        "imagePath": "assets/images/page2.png",
        "color": "#FFBD59",
        "title": "Делитесь своими творениями",
        "description": "Покажите свои кулинарные навыки! Загружайте фотографии, видео или делитесь своими рецептами на YouTube, чтобы вдохновить других."
    },
    {
        "imagePath": "assets/images/page3.png",
        "color": "#FDA976",
        "title": "Умные предложения на основе ингредиентов",
        "description": "Не знаете, что приготовить? Сфотографируйте свои ингредиенты, и мы предложим рецепты, которые можно приготовить из них."
    }
]
